Workbook

Sheet Assets
B3: Paleta de Cores
B5: # 9BC848 | C5: Xbox Color | E5: # E8E6E9 | F5: negative zone
B6: # 22C55E | C6: Xbox Color
B7: # 2AE6B1 | C7: Menus
B8: # 5BF6A8 | C8: Menus
B12: Logos | J12: ícones

Sheet Base
A1: Subscriber ID | B1: Name | C1: Plan | D1: Start Date | E1: Auto Renewal | F1: Subscription Price | G1: Subscription Type | H1: EA Play Season Pass | I1: EA Play Season Pass Price | J1: Minecraft Season Pass | K1: Minecraft Season Pass Price | L1: Coupon Value | M1: Total Value
A2: 3231 | B2: João Silva | C2: Ultimate | D2: 45292 | E2: Yes | F2: 15 | G2: Monthly | H2: Yes | I2: 30 | J2: Yes | K2: 20 | L2: 5 | M2: 60
A3: 3232 | B3: Maria Oliveira | C3: Core | D3: 45306 | E3: No | F3: 5 | G3: Annual | H3: No | I3: - | J3: No | K3: 0 | L3: 0 | M3: 5
A4: 3233 | B4: Lucas Fernandes | C4: Standard | D4: 45332 | E4: Yes | F4: 10 | G4: Quarterly | H4: No | I4: - | J4: Yes | K4: 20 | L4: 10 | M4: 20
A5: 3234 | B5: Ana Souza | C5: Ultimate | D5: 45342 | E5: No | F5: 15 | G5: Monthly | H5: Yes | I5: 30 | J5: Yes | K5: 20 | L5: 3 | M5: 62
A6: 3235 | B6: Pedro Gonçalves | C6: Core | D6: 45356 | E6: Yes | F6: 5 | G6: Monthly | H6: No | I6: - | J6: No | K6: 0 | L6: 1 | M6: 4
A7: 3236 | B7: Felipe Costa | C7: Standard | D7: 45353 | E7: No | F7: 10 | G7: Monthly | H7: No | I7: - | J7: Yes | K7: 20 | L7: 2 | M7: 28
A8: 3237 | B8: Camila Ribeiro | C8: Ultimate | D8: 45354 | E8: Yes | F8: 15 | G8: Quarterly | H8: Yes | I8: 30 | J8: Yes | K8: 20 | L8: 10 | M8: 55
A9: 3238 | B9: André Mendes | C9: Core | D9: 45355 | E9: Yes | F9: 5 | G9: Annual | H9: No | I9: - | J9: No | K9: 0 | L9: 0 | M9: 5
A10: 3239 | B10: Sofia Almeida | C10: Ultimate | D10: 45356 | E10: No | F10: 15 | G10: Monthly | H10: Yes | I10: 30 | J10: Yes | K10: 20 | L10: 5 | M10: 60
A11: 3240 | B11: Bruno Martins | C11: Standard | D11: 45357 | E11: Yes | F11: 10 | G11: Quarterly | H11: No | I11: - | J11: Yes | K11: 20 | L11: 15 | M11: 15
A12: 3241 | B12: Rita Castro | C12: Core | D12: 45358 | E12: No | F12: 5 | G12: Monthly | H12: No | I12: - | J12: No | K12: 0 | L12: 1 | M12: 4
A13: 3242 | B13: Marco Túlio | C13: Ultimate | D13: 45359 | E13: Yes | F13: 15 | G13: Annual | H13: Yes | I13: 30 | J13: Yes | K13: 20 | L13: 20 | M13: 45
A14: 3243 | B14: Lívia Silveira | C14: Standard | D14: 45360 | E14: No | F14: 10 | G14: Monthly | H14: No | I14: - | J14: Yes | K14: 20 | L14: 10 | M14: 20
A15: 3244 | B15: Diogo Sousa | C15: Core | D15: 45361 | E15: Yes | F15: 5 | G15: Quarterly | H15: No | I15: - | J15: No | K15: 0 | L15: 0 | M15: 5
A16: 3245 | B16: Fernanda Lima | C16: Ultimate | D16: 45362 | E16: No | F16: 15 | G16: Monthly | H16: Yes | I16: 30 | J16: Yes | K16: 20 | L16: 8 | M16: 57
A17: 3246 | B17: Caio Pereira | C17: Standard | D17: 45363 | E17: Yes | F17: 10 | G17: Annual | H17: No | I17: - | J17: Yes | K17: 20 | L17: 12 | M17: 18
A18: 3247 | B18: Beatriz Gomes | C18: Core | D18: 45364 | E18: No | F18: 5 | G18: Monthly | H18: No | I18: - | J18: No | K18: 0 | L18: 2 | M18: 3
A19: 3248 | B19: Cesar Oliveira | C19: Ultimate | D19: 45365 | E19: Yes | F19: 15 | G19: Quarterly | H19: Yes | I19: 30 | J19: Yes | K19: 20 | L19: 7 | M19: 58
A20: 3249 | B20: Débora Machado | C20: Standard | D20: 45366 | E20: No | F20: 10 | G20: Monthly | H20: No | I20: - | J20: Yes | K20: 20 | L20: 5 | M20: 25
A21: 3250 | B21: Eduardo Vargas | C21: Core | D21: 45367 | E21: Yes | F21: 5 | G21: Annual | H21: No | I21: - | J21: No | K21: 0 | L21: 0 | M21: 5
A22: 3251 | B22: Gabriela Santos | C22: Ultimate | D22: 45368 | E22: No | F22: 15 | G22: Monthly | H22: Yes | I22: 30 | J22: Yes | K22: 20 | L22: 3 | M22: 62
A23: 3252 | B23: Henrique Dias | C23: Standard | D23: 45369 | E23: Yes | F23: 10 | G23: Quarterly | H23: No | I23: - | J23: Yes | K23: 20 | L23: 15 | M23: 15
A24: 3253 | B24: Isabela Moreira | C24: Core | D24: 45370 | E24: No | F24: 5 | G24: Monthly | H24: No | I24: - | J24: No | K24: 0 | L24: 1 | M24: 4
A25: 3254 | B25: Joaquim Barbosa | C25: Ultimate | D25: 45371 | E25: Yes | F25: 15 | G25: Annual | H25: Yes | I25: 30 | J25: Yes | K25: 20 | L25: 20 | M25: 45
A26: 3255 | B26: Lara Rocha | C26: Standard | D26: 45372 | E26: No | F26: 10 | G26: Monthly | H26: No | I26: - | J26: Yes | K26: 20 | L26: 10 | M26: 20
A27: 3256 | B27: Matheus Silva | C27: Core | D27: 45373 | E27: Yes | F27: 5 | G27: Quarterly | H27: No | I27: - | J27: No | K27: 0 | L27: 0 | M27: 5
A28: 3257 | B28: Nicole Costa | C28: Ultimate | D28: 45374 | E28: No | F28: 15 | G28: Monthly | H28: Yes | I28: 30 | J28: Yes | K28: 20 | L28: 5 | M28: 60
A29: 3258 | B29: Otávio Mendonça | C29: Standard | D29: 45375 | E29: Yes | F29: 10 | G29: Annual | H29: No | I29: - | J29: Yes | K29: 20 | L29: 15 | M29: 15
A30: 3259 | B30: Paula Ferreira | C30: Core | D30: 45376 | E30: No | F30: 5 | G30: Monthly | H30: No | I30: - | J30: No | K30: 0 | L30: 1 | M30: 4
A31: 3260 | B31: Raquel Alves | C31: Ultimate | D31: 45377 | E31: Yes | F31: 15 | G31: Quarterly | H31: Yes | I31: 30 | J31: Yes | K31: 20 | L31: 7 | M31: 58
A32: 3261 | B32: Samuel Pires | C32: Standard | D32: 45378 | E32: No | F32: 10 | G32: Monthly | H32: No | I32: - | J32: Yes | K32: 20 | L32: 10 | M32: 20
A33: 3262 | B33: Tânia Barros | C33: Core | D33: 45379 | E33: Yes | F33: 5 | G33: Annual | H33: No | I33: - | J33: No | K33: 0 | L33: 0 | M33: 5
A34: 3263 | B34: Vinicius Lima | C34: Ultimate | D34: 45380 | E34: No | F34: 15 | G34: Monthly | H34: Yes | I34: 30 | J34: Yes | K34: 20 | L34: 3 | M34: 62
A35: 3264 | B35: Yasmin Teixeira | C35: Standard | D35: 45381 | E35: Yes | F35: 10 | G35: Quarterly | H35: No | I35: - | J35: Yes | K35: 20 | L35: 15 | M35: 15
A36: 3265 | B36: Zé Carlos | C36: Core | D36: 45382 | E36: No | F36: 5 | G36: Monthly | H36: No | I36: - | J36: No | K36: 0 | L36: 1 | M36: 4
A37: 3266 | B37: Amanda Nogueira | C37: Core | D37: 45383 | E37: Yes | F37: 5 | G37: Monthly | H37: No | I37: - | J37: No | K37: 0 | L37: 0 | M37: 5
A38: 3267 | B38: Bruno Cavalheiro | C38: Ultimate | D38: 45384 | E38: No | F38: 15 | G38: Quarterly | H38: Yes | I38: 30 | J38: Yes | K38: 20 | L38: 7 | M38: 58
A39: 3268 | B39: Carla Dias | C39: Standard | D39: 45385 | E39: Yes | F39: 10 | G39: Annual | H39: No | I39: - | J39: Yes | K39: 20 | L39: 10 | M39: 20
A40: 3269 | B40: Diego Fontes | C40: Core | D40: 45386 | E40: No | F40: 5 | G40: Quarterly | H40: No | I40: - | J40: No | K40: 0 | L40: 1 | M40: 4
A41: 3270 | B41: Eunice Lima | C41: Ultimate | D41: 45387 | E41: Yes | F41: 15 | G41: Monthly | H41: Yes | I41: 30 | J41: Yes | K41: 20 | L41: 15 | M41: 50
A42: 3271 | B42: Fábio Martins | C42: Standard | D42: 45388 | E42: No | F42: 10 | G42: Monthly | H42: No | I42: - | J42: Yes | K42: 20 | L42: 5 | M42: 25
A43: 3272 | B43: Gisele Araújo | C43: Core | D43: 45389 | E43: Yes | F43: 5 | G43: Annual | H43: No | I43: - | J43: No | K43: 0 | L43: 0 | M43: 5
A44: 3273 | B44: Hélio Castro | C44: Ultimate | D44: 45390 | E44: No | F44: 15 | G44: Quarterly | H44: Yes | I44: 30 | J44: Yes | K44: 20 | L44: 20 | M44: 45
A45: 3274 | B45: Ingrid Menezes | C45: Standard | D45: 45391 | E45: Yes | F45: 10 | G45: Quarterly | H45: No | I45: - | J45: Yes | K45: 20 | L45: 12 | M45: 18
A46: 3275 | B46: Jorge Baptista | C46: Core | D46: 45392 | E46: No | F46: 5 | G46: Monthly | H46: No | I46: - | J46: No | K46: 0 | L46: 2 | M46: 3
A47: 3276 | B47: Kléber Oliveira | C47: Ultimate | D47: 45393 | E47: Yes | F47: 15 | G47: Annual | H47: Yes | I47: 30 | J47: Yes | K47: 20 | L47: 5 | M47: 60
A48: 3277 | B48: Luciana Freitas | C48: Standard | D48: 45394 | E48: No | F48: 10 | G48: Monthly | H48: No | I48: - | J48: Yes | K48: 20 | L48: 10 | M48: 20
A49: 3278 | B49: Márcia Eller | C49: Core | D49: 45395 | E49: Yes | F49: 5 | G49: Quarterly | H49: No | I49: - | J49: No | K49: 0 | L49: 0 | M49: 5
A50: 3279 | B50: Nilo Peçanha | C50: Ultimate | D50: 45396 | E50: No | F50: 15 | G50: Monthly | H50: Yes | I50: 30 | J50: Yes | K50: 20 | L50: 3 | M50: 62
A51: 3280 | B51: Oscar Neves | C51: Standard | D51: 45397 | E51: Yes | F51: 10 | G51: Annual | H51: No | I51: - | J51: Yes | K51: 20 | L51: 15 | M51: 15
A52: 3281 | B52: Patrícia Soares | C52: Core | D52: 45398 | E52: No | F52: 5 | G52: Monthly | H52: No | I52: - | J52: No | K52: 0 | L52: 1 | M52: 4
A53: 3282 | B53: Quirino Gonçalves | C53: Ultimate | D53: 45399 | E53: Yes | F53: 15 | G53: Quarterly | H53: Yes | I53: 30 | J53: Yes | K53: 20 | L53: 7 | M53: 58
A54: 3283 | B54: Raul Machado | C54: Standard | D54: 45400 | E54: No | F54: 10 | G54: Monthly | H54: No | I54: - | J54: Yes | K54: 20 | L54: 10 | M54: 20
A55: 3284 | B55: Sônia Lobo | C55: Core | D55: 45401 | E55: Yes | F55: 5 | G55: Annual | H55: No | I55: - | J55: No | K55: 0 | L55: 0 | M55: 5
A56: 3285 | B56: Tiago Ramos | C56: Ultimate | D56: 45402 | E56: No | F56: 15 | G56: Monthly | H56: Yes | I56: 30 | J56: Yes | K56: 20 | L56: 20 | M56: 45
A57: 3286 | B57: Ugo Pires | C57: Standard | D57: 45403 | E57: Yes | F57: 10 | G57: Quarterly | H57: No | I57: - | J57: Yes | K57: 20 | L57: 15 | M57: 15
A58: 3287 | B58: Valéria Nobre | C58: Core | D58: 45404 | E58: No | F58: 5 | G58: Monthly | H58: No | I58: - | J58: No | K58: 0 | L58: 1 | M58: 4
A59: 3288 | B59: William Siqueira | C59: Ultimate | D59: 45405 | E59: Yes | F59: 15 | G59: Annual | H59: Yes | I59: 30 | J59: Yes | K59: 20 | L59: 3 | M59: 62
A60: 3289 | B60: Xuxa Meneghel | C60: Standard | D60: 45406 | E60: No | F60: 10 | G60: Monthly | H60: No | I60: - | J60: Yes | K60: 20 | L60: 10 | M60: 20
A61: 3290 | B61: Yara Figueiredo | C61: Core | D61: 45407 | E61: Yes | F61: 5 | G61: Quarterly | H61: No | I61: - | J61: No | K61: 0 | L61: 0 | M61: 5
A62: 3291 | B62: Zacarias Alves | C62: Ultimate | D62: 45408 | E62: No | F62: 15 | G62: Monthly | H62: Yes | I62: 30 | J62: Yes | K62: 20 | L62: 5 | M62: 60
A63: 3292 | B63: Amanda Bynes | C63: Standard | D63: 45409 | E63: Yes | F63: 10 | G63: Annual | H63: No | I63: - | J63: Yes | K63: 20 | L63: 15 | M63: 15
A64: 3293 | B64: Bruno Mars | C64: Core | D64: 45410 | E64: No | F64: 5 | G64: Monthly | H64: No | I64: - | J64: No | K64: 0 | L64: 1 | M64: 4
A65: 3294 | B65: Carla Bruni | C65: Ultimate | D65: 45411 | E65: Yes | F65: 15 | G65: Quarterly | H65: Yes | I65: 30 | J65: Yes | K65: 20 | L65: 20 | M65: 45
A66: 3295 | B66: Diego Maradona | C66: Standard | D66: 45412 | E66: No | F66: 10 | G66: Monthly | H66: No | I66: - | J66: Yes | K66: 20 | L66: 5 | M66: 25
A67: 3296 | B67: Estela Marques | C67: Core | D67: 45413 | E67: No | F67: 5 | G67: Monthly | H67: No | I67: - | J67: No | K67: 0 | L67: 0 | M67: 5
A68: 3297 | B68: Fábio Nobre | C68: Ultimate | D68: 45414 | E68: Yes | F68: 15 | G68: Quarterly | H68: Yes | I68: 30 | J68: Yes | K68: 20 | L68: 7 | M68: 58
A69: 3298 | B69: Gabriel Oliveira | C69: Standard | D69: 45415 | E69: No | F69: 10 | G69: Annual | H69: No | I69: - | J69: Yes | K69: 20 | L69: 10 | M69: 20
A70: 3299 | B70: Helena Santos | C70: Core | D70: 45416 | E70: Yes | F70: 5 | G70: Quarterly | H70: No | I70: - | J70: No | K70: 0 | L70: 1 | M70: 4
A71: 3300 | B71: Ivan Carvalho | C71: Ultimate | D71: 45417 | E71: No | F71: 15 | G71: Monthly | H71: Yes | I71: 30 | J71: Yes | K71: 20 | L71: 15 | M71: 50
A72: 3301 | B72: Júlia Ferreira | C72: Standard | D72: 45418 | E72: Yes | F72: 10 | G72: Monthly | H72: No | I72: - | J72: Yes | K72: 20 | L72: 5 | M72: 25
A73: 3302 | B73: Karla Alves | C73: Core | D73: 45419 | E73: No | F73: 5 | G73: Annual | H73: No | I73: - | J73: No | K73: 0 | L73: 0 | M73: 5
A74: 3303 | B74: Lucas Mendes | C74: Ultimate | D74: 45420 | E74: Yes | F74: 15 | G74: Quarterly | H74: Yes | I74: 30 | J74: Yes | K74: 20 | L74: 20 | M74: 45
A75: 3304 | B75: Mônica Gomes | C75: Standard | D75: 45421 | E75: No | F75: 10 | G75: Quarterly | H75: No | I75: - | J75: Yes | K75: 20 | L75: 12 | M75: 18
A76: 3305 | B76: Norberto Queiroz | C76: Core | D76: 45422 | E76: Yes | F76: 5 | G76: Monthly | H76: No | I76: - | J76: No | K76: 0 | L76: 2 | M76: 3
A77: 3306 | B77: Otávio Barros | C77: Ultimate | D77: 45423 | E77: No | F77: 15 | G77: Annual | H77: Yes | I77: 30 | J77: Yes | K77: 20 | L77: 5 | M77: 60
A78: 3307 | B78: Paula Vieira | C78: Standard | D78: 45424 | E78: Yes | F78: 10 | G78: Monthly | H78: No | I78: - | J78: Yes | K78: 20 | L78: 10 | M78: 20
A79: 3308 | B79: Quentin Ramos | C79: Core | D79: 45425 | E79: No | F79: 5 | G79: Quarterly | H79: No | I79: - | J79: No | K79: 0 | L79: 0 | M79: 5
A80: 3309 | B80: Raquel Novaes | C80: Ultimate | D80: 45426 | E80: Yes | F80: 15 | G80: Monthly | H80: Yes | I80: 30 | J80: Yes | K80: 20 | L80: 3 | M80: 62
A81: 3310 | B81: Samantha Lopes | C81: Standard | D81: 45427 | E81: No | F81: 10 | G81: Annual | H81: No | I81: - | J81: Yes | K81: 20 | L81: 15 | M81: 15
A82: 3311 | B82: Tiago Martins | C82: Core | D82: 45428 | E82: Yes | F82: 5 | G82: Monthly | H82: No | I82: - | J82: No | K82: 0 | L82: 1 | M82: 4
A83: 3312 | B83: Ulysses Guimarães | C83: Ultimate | D83: 45429 | E83: No | F83: 15 | G83: Quarterly | H83: Yes | I83: 30 | J83: Yes | K83: 20 | L83: 7 | M83: 58
A84: 3313 | B84: Vanessa Silva | C84: Standard | D84: 45430 | E84: Yes | F84: 10 | G84: Monthly | H84: No | I84: - | J84: Yes | K84: 20 | L84: 10 | M84: 20
A85: 3314 | B85: William Carneiro | C85: Core | D85: 45431 | E85: No | F85: 5 | G85: Annual | H85: No | I85: - | J85: No | K85: 0 | L85: 0 | M85: 5
A86: 3315 | B86: Ximena Rocha | C86: Ultimate | D86: 45432 | E86: Yes | F86: 15 | G86: Monthly | H86: Yes | I86: 30 | J86: Yes | K86: 20 | L86: 20 | M86: 45
A87: 3316 | B87: Yasmin Figueiredo | C87: Standard | D87: 45433 | E87: No | F87: 10 | G87: Quarterly | H87: No | I87: - | J87: Yes | K87: 20 | L87: 15 | M87: 15
A88: 3317 | B88: Zara Cunha | C88: Core | D88: 45434 | E88: Yes | F88: 5 | G88: Monthly | H88: No | I88: - | J88: No | K88: 0 | L88: 1 | M88: 4
A89: 3318 | B89: Alan Teixeira | C89: Ultimate | D89: 45435 | E89: No | F89: 15 | G89: Annual | H89: Yes | I89: 30 | J89: Yes | K89: 20 | L89: 3 | M89: 62
A90: 3319 | B90: Bárbara Oliveira | C90: Standard | D90: 45436 | E90: Yes | F90: 10 | G90: Monthly | H90: No | I90: - | J90: Yes | K90: 20 | L90: 10 | M90: 20
A91: 3320 | B91: Carlos Junqueira | C91: Core | D91: 45437 | E91: No | F91: 5 | G91: Quarterly | H91: No | I91: - | J91: No | K91: 0 | L91: 0 | M91: 5
A92: 3321 | B92: Daniela Moura | C92: Ultimate | D92: 45438 | E92: Yes | F92: 15 | G92: Monthly | H92: Yes | I92: 30 | J92: Yes | K92: 20 | L92: 5 | M92: 60
A93: 3322 | B93: Eduardo Lima | C93: Standard | D93: 45439 | E93: No | F93: 10 | G93: Annual | H93: No | I93: - | J93: Yes | K93: 20 | L93: 15 | M93: 15
A94: 3323 | B94: Fabiana Araújo | C94: Core | D94: 45440 | E94: Yes | F94: 5 | G94: Monthly | H94: No | I94: - | J94: No | K94: 0 | L94: 1 | M94: 4
A95: 3324 | B95: Geraldo Ribeiro | C95: Ultimate | D95: 45441 | E95: No | F95: 15 | G95: Quarterly | H95: Yes | I95: 30 | J95: Yes | K95: 20 | L95: 20 | M95: 45
A96: 3325 | B96: Héctor Vargas | C96: Standard | D96: 45442 | E96: Yes | F96: 10 | G96: Quarterly | H96: No | I96: - | J96: Yes | K96: 20 | L96: 15 | M96: 15
A97: 3326 | B97: Isabela Fonseca | C97: Core | D97: 45443 | E97: No | F97: 5 | G97: Annual | H97: No | I97: - | J97: No | K97: 0 | L97: 0 | M97: 5
A98: 3327 | B98: João Pedro Almeida | C98: Ultimate | D98: 45444 | E98: Yes | F98: 15 | G98: Monthly | H98: Yes | I98: 30 | J98: Yes | K98: 20 | L98: 7 | M98: 58
A99: 3328 | B99: Klara Costa | C99: Standard | D99: 45445 | E99: No | F99: 10 | G99: Annual | H99: No | I99: - | J99: Yes | K99: 20 | L99: 10 | M99: 20
A100: 3329 | B100: Luciana Mendes | C100: Core | D100: 45446 | E100: Yes | F100: 5 | G100: Quarterly | H100: No | I100: - | J100: No | K100: 0 | L100: 1 | M100: 4
...

Sheet Calculos
A1: Mês | B1: Receita Mensal | D1: Plano | E1: Receita por Plano | G1: Tipo | H1: Receita por Tipo | J1: Renovação | K1: Qtde | L1: Receita | N1: KPI | O1: Valor | Q1: Rank | R1: Cliente | S1: Receita
A2: 45292 | B2: =SUMIFS(Base!$M$2:$M$296,Base!$D$2:$D$296,">="&A2,Base!$D$2:$D$296,"<"&EDATE(A2,1)) | D2: Ultimate | E2: =SUMIF(Base!$C$2:$C$296,D2,Base!$M$2:$M$296) | G2: Monthly | H2: =SUMIF(Base!$G$2:$G$296,G2,Base!$M$2:$M$296) | J2: Yes | K2: =COUNTIF(Base!$E$2:$E$296,J2) | L2: =SUMIF(Base!$E$2:$E$296,J2,Base!$M$2:$M$296) | N2: Receita Total | O2: =SUM(B2:B13) | Q2: 1 | R2: Joana Silveira | S2: 120
A3: 45323 | B3: =SUMIFS(Base!$M$2:$M$296,Base!$D$2:$D$296,">="&A3,Base!$D$2:$D$296,"<"&EDATE(A3,1)) | D3: Standard | E3: =SUMIF(Base!$C$2:$C$296,D3,Base!$M$2:$M$296) | G3: Quarterly | H3: =SUMIF(Base!$G$2:$G$296,G3,Base!$M$2:$M$296) | J3: No | K3: =COUNTIF(Base!$E$2:$E$296,J3) | L3: =SUMIF(Base!$E$2:$E$296,J3,Base!$M$2:$M$296) | N3: Ticket Médio | O3: =AVERAGE(Base!$M$2:$M$296) | Q3: 2 | R3: Geraldo Ribeiro | S3: 107
A4: 45352 | B4: =SUMIFS(Base!$M$2:$M$296,Base!$D$2:$D$296,">="&A4,Base!$D$2:$D$296,"<"&EDATE(A4,1)) | D4: Core | E4: =SUMIF(Base!$C$2:$C$296,D4,Base!$M$2:$M$296) | G4: Annual | H4: =SUMIF(Base!$G$2:$G$296,G4,Base!$M$2:$M$296) | N4: % Auto Renewal | O4: =COUNTIF(Base!$E$2:$E$296,"Yes")/COUNTA(Base!$E$2:$E$296) | Q4: 3 | R4: Daniela Moura | S4: 105
A5: 45383 | B5: =SUMIFS(Base!$M$2:$M$296,Base!$D$2:$D$296,">="&A5,Base!$D$2:$D$296,"<"&EDATE(A5,1)) | N5: Assinantes | O5: =COUNTA(Base!$A$2:$A$296) | Q5: 4 | R5: Kléber Oliveira | S5: 80
A6: 45413 | B6: =SUMIFS(Base!$M$2:$M$296,Base!$D$2:$D$296,">="&A6,Base!$D$2:$D$296,"<"&EDATE(A6,1)) | Q6: 5 | R6: Xuxa Meneghel | S6: 70
A7: 45444 | B7: =SUMIFS(Base!$M$2:$M$296,Base!$D$2:$D$296,">="&A7,Base!$D$2:$D$296,"<"&EDATE(A7,1)) | Q7: 6 | R7: Elisa Neves | S7: 67
A8: 45474 | B8: =SUMIFS(Base!$M$2:$M$296,Base!$D$2:$D$296,">="&A8,Base!$D$2:$D$296,"<"&EDATE(A8,1)) | Q8: 7 | R8: Raquel Novaes | S8: 62
A9: 45505 | B9: =SUMIFS(Base!$M$2:$M$296,Base!$D$2:$D$296,">="&A9,Base!$D$2:$D$296,"<"&EDATE(A9,1)) | Q9: 8 | R9: Gabriel Santos | S9: 62
A10: 45536 | B10: =SUMIFS(Base!$M$2:$M$296,Base!$D$2:$D$296,">="&A10,Base!$D$2:$D$296,"<"&EDATE(A10,1)) | Q10: 9 | R10: Patrícia Leite | S10: 62
A11: 45566 | B11: =SUMIFS(Base!$M$2:$M$296,Base!$D$2:$D$296,">="&A11,Base!$D$2:$D$296,"<"&EDATE(A11,1)) | Q11: 10 | R11: Elisa Correia | S11: 62
A12: 45597 | B12: =SUMIFS(Base!$M$2:$M$296,Base!$D$2:$D$296,">="&A12,Base!$D$2:$D$296,"<"&EDATE(A12,1))
A13: 45627 | B13: =SUMIFS(Base!$M$2:$M$296,Base!$D$2:$D$296,">="&A13,Base!$D$2:$D$296,"<"&EDATE(A13,1))

Sheet Dashboard
A1: Dashboard de Vendas - Xbox Game Pass
A3: Visão geral da base de assinaturas de 2024 com foco em receita, perfil de compra e clientes de maior valor
A5: Receita Total | D5: Ticket Médio | G5: % Auto Renewal | J5: Assinantes
A6: =Calculos!O2 | D6: =Calculos!O3 | G6: =Calculos!O4 | J6: =Calculos!O5
A9: Receita por Plano | G9: Receita Mensal
A20: Legenda: receita total por plano. | G20: Legenda: evolução mensal da receita em 2024.
A22: Receita por Tipo de Assinatura | G22: Renovação Automática
A33: Legenda: comparação entre planos mensal, trimestral e anual. | G33: Legenda: participação de clientes com e sem renovação automática.
A35: Top 10 Clientes por Receita (agregado por cliente)
A36: Rank | B36: Cliente | C36: Receita
A37: 1 | B37: Joana Silveira | C37: 120
A38: 2 | B38: Geraldo Ribeiro | C38: 107
A39: 3 | B39: Daniela Moura | C39: 105
A40: 4 | B40: Kléber Oliveira | C40: 80
A41: 5 | B41: Xuxa Meneghel | C41: 70
A42: 6 | B42: Elisa Neves | C42: 67
A43: 7 | B43: Raquel Novaes | C43: 62
A44: 8 | B44: Gabriel Santos | C44: 62
A45: 9 | B45: Patrícia Leite | C45: 62
A46: 10 | B46: Elisa Correia | C46: 62
A47: Verificação feita: o ranking de clientes foi consolidado por nome, corrigindo a repetição indevida de um único cliente.
